[
  {
    "id": 1,
    "id_number": "1",
    "name": "Spring Roll (2)",
    "price": "4.95",
    "category": "Appetizers"
  },
  {
    "id": 2,
    "id_number": "2",
    "name": "Egg Roll",
    "price": "2.00",
    "category": "Appetizers"
  },
  {
    "id": 3,
    "id_number": "3",
    "name": "Fried Biscuit (10)",
    "price": "5.95",
    "category": "Appetizers"
  },
  {
    "id": 4,
    "id_number": "4",
    "name": "Fried Shrimp (11)",
    "price": "7.25",
    "category": "Appetizers"
  },
  {
    "id": 5,
    "id_number": "5",
    "name": "Fried or Steamed Dumplings (8)",
    "price": "7.95",
    "category": "Appetizers"
  },
  {
    "id": 6,
    "id_number": "6",
    "name": "Crab Rangoon (8)",
    "price": "6.95",
    "category": "Appetizers"
  },
  {
    "id": 7,
    "id_number": "7",
    "name": "Potato Skin (6)",
    "price": "6.95",
    "category": "Appetizers"
  },
  {
    "id": 8,
    "id_number": "8",
    "name": "Fried Wonton (12)",
    "price": "5.95",
    "category": "Appetizers"
  },
  {
    "id": 9,
    "id_number": "9",
    "name": "Chicken Teriyaki (5)",
    "price": "6.95",
    "category": "Appetizers"
  },
  {
    "id": 10,
    "id_number": "9.5",
    "name": "Corn Nuggets (18)",
    "price": "6.95",
    "category": "Appetizers"
  },
  {
    "id": 11,
    "id_number": "10",
    "name": "Wonton Soup",
    "price": "5.50",
    "category": "Soups"
  },
  {
    "id": 12,
    "id_number": "11",
    "name": "Egg Drop Soup",
    "price": "5.50",
    "category": "Soups"
  },
  {
    "id": 13,
    "id_number": "12",
    "name": "Chicken Noodle or Rice Soup",
    "price": "5.50",
    "category": "Soups"
  },
  {
    "id": 14,
    "id_number": "13",
    "name": "Hot & Sour Soup",
    "price": "6.50",
    "category": "Soups"
  },
  {
    "id": 15,
    "id_number": "14",
    "name": "Vegetable Soup",
    "price": "5.50",
    "category": "Soups"
  },
  {
    "id": 16,
    "id_number": "15",
    "name": "House Special Soup",
    "price": "7.75",
    "category": "Soups"
  },
  {
    "id": 17,
    "id_number": "16",
    "name": "Seafood Soup",
    "price": "7.75",
    "category": "Soups"
  },
  {
    "id": 18,
    "id_number": "17",
    "name": "Chicken Chow Mein",
    "price": "8.95",
    "category": "Chow Mein"
  },
  {
    "id": 19,
    "id_number": "18",
    "name": "Roast Pork Chow Mein",
    "price": "8.95",
    "category": "Chow Mein"
  },
  {
    "id": 20,
    "id_number": "19",
    "name": "Beef Chow Mein",
    "price": "8.95",
    "category": "Chow Mein"
  },
  {
    "id": 21,
    "id_number": "20",
    "name": "Shrimp Chow Mein",
    "price": "8.95",
    "category": "Chow Mein"
  },
  {
    "id": 22,
    "id_number": "21",
    "name": "Vegetable Chow Mein",
    "price": "8.95",
    "category": "Chow Mein"
  },
  {
    "id": 23,
    "id_number": "22",
    "name": "House Special Chow Mein",
    "price": "8.95",
    "category": "Chow Mein"
  },
  {
    "id": 24,
    "id_number": "23",
    "name": "Chicken Chop Suey",
    "price": "8.95",
    "category": "Chop Suey"
  },
  {
    "id": 25,
    "id_number": "24",
    "name": "Roast Pork Chop Suey",
    "price": "8.95",
    "category": "Chop Suey"
  },
  {
    "id": 26,
    "id_number": "25",
    "name": "Beef Chop Suey",
    "price": "8.95",
    "category": "Chop Suey"
  },
  {
    "id": 27,
    "id_number": "26",
    "name": "Shrimp Chop Suey",
    "price": "8.95",
    "category": "Chop Suey"
  },
  {
    "id": 28,
    "id_number": "27",
    "name": "Vegetable Chop Suey",
    "price": "8.95",
    "category": "Chop Suey"
  },
  {
    "id": 29,
    "id_number": "28",
    "name": "House Special Chop Suey",
    "price": "8.95",
    "category": "Chop Suey"
  },
  {
    "id": 30,
    "id_number": "29",
    "name": "Plain Lo Mein",
    "price": "8.95",
    "category": "Lo Mein"
  },
  {
    "id": 31,
    "id_number": "30",
    "name": "Vegetable Lo Mein",
    "price": "8.95",
    "category": "Lo Mein"
  },
  {
    "id": 32,
    "id_number": "31",
    "name": "Chicken Lo Mein",
    "price": "8.95",
    "category": "Lo Mein"
  },
  {
    "id": 33,
    "id_number": "32",
    "name": "Roast Pork Lo Mein",
    "price": "8.95",
    "category": "Lo Mein"
  },
  {
    "id": 34,
    "id_number": "33",
    "name": "Beef Lo Mein",
    "price": "8.95",
    "category": "Lo Mein"
  },
  {
    "id": 35,
    "id_number": "34",
    "name": "Shrimp Lo Mein",
    "price": "8.95",
    "category": "Lo Mein"
  },
  {
    "id": 36,
    "id_number": "35",
    "name": "House Special Lo Mein",
    "price": "9.95",
    "category": "Lo Mein"
  },
  {
    "id": 37,
    "id_number": "36",
    "name": "Roast Pork Mei Fun",
    "price": "8.75",
    "category": "Mei Fun"
  },
  {
    "id": 38,
    "id_number": "37",
    "name": "Chicken Mei Fun",
    "price": "8.75",
    "category": "Mei Fun"
  },
  {
    "id": 39,
    "id_number": "38",
    "name": "Shrimp Mei Fun",
    "price": "8.75",
    "category": "Mei Fun"
  },
  {
    "id": 40,
    "id_number": "39",
    "name": "Beef Mei Fun",
    "price": "8.75",
    "category": "Mei Fun"
  },
  {
    "id": 41,
    "id_number": "40",
    "name": "Vegetable Mei Fun",
    "price": "8.75",
    "category": "Mei Fun"
  },
  {
    "id": 42,
    "id_number": "41",
    "name": "House Special Mei Fun",
    "price": "10.25",
    "category": "Mei Fun"
  },
  {
    "id": 43,
    "id_number": "42",
    "name": "Singapore Mei Fun (Spicy)",
    "price": "10.25",
    "category": "Mei Fun"
  },
  {
    "id": 44,
    "id_number": "43",
    "name": "Plain Fried Rice",
    "price": "8.95",
    "category": "Fried Rice"
  },
  {
    "id": 45,
    "id_number": "44",
    "name": "Vegetable Fried Rice",
    "price": "8.95",
    "category": "Fried Rice"
  },
  {
    "id": 46,
    "id_number": "45",
    "name": "Chicken Fried Rice",
    "price": "9.75",
    "category": "Fried Rice"
  },
  {
    "id": 47,
    "id_number": "46",
    "name": "Roast Pork Fried Rice",
    "price": "9.75",
    "category": "Fried Rice"
  },
  {
    "id": 48,
    "id_number": "47",
    "name": "Beef Fried Rice",
    "price": "9.75",
    "category": "Fried Rice"
  },
  {
    "id": 49,
    "id_number": "48",
    "name": "Shrimp Fried Rice",
    "price": "9.75",
    "category": "Fried Rice"
  },
  {
    "id": 50,
    "id_number": "49",
    "name": "House Special Fried Rice",
    "price": "10.25",
    "category": "Fried Rice"
  },
  {
    "id": 51,
    "id_number": "50",
    "name": "Mushroom Egg Foo Young",
    "price": "9.75",
    "category": "Egg Foo Young"
  },
  {
    "id": 52,
    "id_number": "51",
    "name": "Chicken Egg Foo Young",
    "price": "9.75",
    "category": "Egg Foo Young"
  },
  {
    "id": 53,
    "id_number": "52",
    "name": "Roast Pork Egg Foo Young",
    "price": "9.75",
    "category": "Egg Foo Young"
  },
  {
    "id": 54,
    "id_number": "53",
    "name": "Beef Egg Foo Young",
    "price": "9.75",
    "category": "Egg Foo Young"
  },
  {
    "id": 55,
    "id_number": "54",
    "name": "Shrimp Egg Foo Young",
    "price": "9.75",
    "category": "Egg Foo Young"
  },
  {
    "id": 56,
    "id_number": "55",
    "name": "Sauteed Broccoli",
    "price": "8.99",
    "category": "Vegetable"
  },
  {
    "id": 57,
    "id_number": "56",
    "name": "Sauteed Chinese Vegetable",
    "price": "8.99",
    "category": "Vegetable"
  },
  {
    "id": 58,
    "id_number": "57",
    "name": "Mixed Vegetable",
    "price": "8.99",
    "category": "Vegetable"
  },
  {
    "id": 59,
    "id_number": "58",
    "name": "String Beans",
    "price": "8.99",
    "category": "Vegetable"
  },
  {
    "id": 60,
    "id_number": "59",
    "name": "Broccoli in Garlic Sauce (Spicy)",
    "price": "8.99",
    "category": "Vegetable"
  },
  {
    "id": 61,
    "id_number": "60",
    "name": "Mixed Vegetable in Garlic Sauce (Spicy)",
    "price": "8.99",
    "category": "Vegetable"
  },
  {
    "id": 62,
    "id_number": "61",
    "name": "Butter Potato",
    "price": "8.99",
    "category": "Vegetable"
  },
  {
    "id": 63,
    "id_number": "62",
    "name": "Shrimp W. Lobster Sauce",
    "price": "10.50",
    "category": "Shrimp"
  },
  {
    "id": 64,
    "id_number": "63",
    "name": "Shrimp W. Vegetable",
    "price": "10.50",
    "category": "Shrimp"
  },
  {
    "id": 65,
    "id_number": "64",
    "name": "Shrimp W. Broccoli",
    "price": "10.50",
    "category": "Shrimp"
  },
  {
    "id": 66,
    "id_number": "65",
    "name": "Shrimp W. Curry Sauce (Spicy)",
    "price": "10.50",
    "category": "Shrimp"
  },
  {
    "id": 67,
    "id_number": "66",
    "name": "Hot & Spicy Shrimp (Spicy)",
    "price": "10.50",
    "category": "Shrimp"
  },
  {
    "id": 68,
    "id_number": "67",
    "name": "Shrimp W. Garlic Sauce (Spicy)",
    "price": "10.50",
    "category": "Shrimp"
  },
  {
    "id": 69,
    "id_number": "68",
    "name": "Shrimp W. Cashew Nuts",
    "price": "10.50",
    "category": "Shrimp"
  },
  {
    "id": 70,
    "id_number": "69",
    "name": "Kung Po Shrimp (Spicy)",
    "price": "10.50",
    "category": "Shrimp"
  },
  {
    "id": 71,
    "id_number": "70",
    "name": "Shrimp W. Mixed Vegetable",
    "price": "10.50",
    "category": "Shrimp"
  },
  {
    "id": 72,
    "id_number": "70.5",
    "name": "Coconut Shrimp",
    "price": "11.50",
    "category": "Shrimp"
  },
  {
    "id": 73,
    "id_number": "70.9",
    "name": "Black Pepper Shrimp",
    "price": "14.99",
    "category": "Shrimp"
  },
  {
    "id": 74,
    "id_number": "71",
    "name": "Beef w. Broccoli",
    "price": "10.25",
    "category": "Beef"
  },
  {
    "id": 75,
    "id_number": "72",
    "name": "Pepper Steak",
    "price": "10.25",
    "category": "Beef"
  },
  {
    "id": 76,
    "id_number": "73",
    "name": "Kung Po Beef w. Peanut (Spicy)",
    "price": "10.25",
    "category": "Beef"
  },
  {
    "id": 77,
    "id_number": "74",
    "name": "Beef w. Garlic Sauce (Spicy)",
    "price": "10.25",
    "category": "Beef"
  },
  {
    "id": 78,
    "id_number": "75",
    "name": "Beef w. Mixed Vegetables",
    "price": "10.25",
    "category": "Beef"
  },
  {
    "id": 79,
    "id_number": "76",
    "name": "Beef Szechuan Style (Spicy)",
    "price": "10.25",
    "category": "Beef"
  },
  {
    "id": 80,
    "id_number": "77",
    "name": "Beef Hunan Style (Spicy)",
    "price": "10.25",
    "category": "Beef"
  },
  {
    "id": 81,
    "id_number": "78",
    "name": "Beef W. Mushroom & Pea Pod",
    "price": "10.25",
    "category": "Beef"
  },
  {
    "id": 82,
    "id_number": "79",
    "name": "Roast Pork W. Broccoli",
    "price": "9.95",
    "category": "Pork"
  },
  {
    "id": 83,
    "id_number": "80",
    "name": "Roast Pork W. Chinese Veg",
    "price": "9.95",
    "category": "Pork"
  },
  {
    "id": 84,
    "id_number": "81",
    "name": "Kung Po Pork (Spicy)",
    "price": "9.95",
    "category": "Pork"
  },
  {
    "id": 85,
    "id_number": "82",
    "name": "Pork Hunan Style (Spicy)",
    "price": "9.95",
    "category": "Pork"
  },
  {
    "id": 86,
    "id_number": "83",
    "name": "Pork In Garlic Sauce (Spicy)",
    "price": "9.95",
    "category": "Pork"
  },
  {
    "id": 87,
    "id_number": "84",
    "name": "Roast Pork W. Cashew Nuts",
    "price": "9.95",
    "category": "Pork"
  },
  {
    "id": 88,
    "id_number": "85",
    "name": "Chicken W. Broccoli",
    "price": "10.25",
    "category": "Chicken"
  },
  {
    "id": 89,
    "id_number": "86",
    "name": "Chicken W. String Beans",
    "price": "10.25",
    "category": "Chicken"
  },
  {
    "id": 90,
    "id_number": "87",
    "name": "Spicy Curry Chicken (Spicy)",
    "price": "10.25",
    "category": "Chicken"
  },
  {
    "id": 91,
    "id_number": "88",
    "name": "Chicken W. Cashew Nuts",
    "price": "10.25",
    "category": "Chicken"
  },
  {
    "id": 92,
    "id_number": "89",
    "name": "Chicken In Garlic Sauce (Spicy)",
    "price": "10.25",
    "category": "Chicken"
  },
  {
    "id": 93,
    "id_number": "90",
    "name": "Chicken Teriyaki",
    "price": "10.25",
    "category": "Chicken"
  },
  {
    "id": 94,
    "id_number": "91",
    "name": "Sweet & Sour Chicken",
    "price": "10.25",
    "category": "Chicken"
  },
  {
    "id": 95,
    "id_number": "92",
    "name": "Kung Po Chicken (Spicy)",
    "price": "10.25",
    "category": "Chicken"
  },
  {
    "id": 96,
    "id_number": "93",
    "name": "Moo Gao Gai Pan",
    "price": "10.25",
    "category": "Chicken"
  },
  {
    "id": 97,
    "id_number": "94",
    "name": "Chicken W. Mixed Vegetable",
    "price": "10.25",
    "category": "Chicken"
  },
  {
    "id": 98,
    "id_number": "95",
    "name": "Chicken W. Broccoli In Garlic Sauce",
    "price": "10.25",
    "category": "Chicken"
  },
  {
    "id": 99,
    "id_number": "96",
    "name": "Chicken Hunan Style (Spicy)",
    "price": "10.25",
    "category": "Chicken"
  },
  {
    "id": 100,
    "id_number": "97",
    "name": "Chicken Szechuan Style (Spicy)",
    "price": "10.25",
    "category": "Chicken"
  },
  {
    "id": 101,
    "id_number": "98",
    "name": "Hot & Spicy Chicken",
    "price": "10.25",
    "category": "Chicken"
  },
  {
    "id": 102,
    "id_number": "99",
    "name": "Black Pepper Chicken",
    "price": "10.25",
    "category": "Chicken"
  },
  {
    "id": 103,
    "id_number": "100",
    "name": "Bourbon Chicken",
    "price": "10.25",
    "category": "Chicken"
  },
  {
    "id": 104,
    "id_number": "L1",
    "name": "Chicken Chow Mein",
    "price": "8.25",
    "category": "Lunch Combos"
  },
  {
    "id": 105,
    "id_number": "L2",
    "name": "Shrimp Chow Mein",
    "price": "8.25",
    "category": "Lunch Combos"
  },
  {
    "id": 106,
    "id_number": "L3",
    "name": "Roast Pork Egg Foo Young",
    "price": "8.25",
    "category": "Lunch Combos"
  },
  {
    "id": 107,
    "id_number": "L4",
    "name": "Roast Pork W. Chinese Veg",
    "price": "8.25",
    "category": "Lunch Combos"
  },
  {
    "id": 108,
    "id_number": "L5",
    "name": "Chicken Lo Mein (Soft Noodles)",
    "price": "8.25",
    "category": "Lunch Combos"
  },
  {
    "id": 109,
    "id_number": "L6",
    "name": "Pork Lo Mein (Soft Noodles)",
    "price": "8.25",
    "category": "Lunch Combos"
  },
  {
    "id": 110,
    "id_number": "L7",
    "name": "Pepper Steak W. Onion",
    "price": "8.25",
    "category": "Lunch Combos"
  },
  {
    "id": 111,
    "id_number": "L8",
    "name": "Moo Goo Gai Pan",
    "price": "8.25",
    "category": "Lunch Combos"
  },
  {
    "id": 112,
    "id_number": "L9",
    "name": "Sweet & Sour Chicken",
    "price": "8.25",
    "category": "Lunch Combos"
  },
  {
    "id": 113,
    "id_number": "L10",
    "name": "Shrimp W. Lobster Sauce",
    "price": "8.25",
    "category": "Lunch Combos"
  },
  {
    "id": 114,
    "id_number": "L11",
    "name": "Shrimp W. Broccoli",
    "price": "8.25",
    "category": "Lunch Combos"
  },
  {
    "id": 115,
    "id_number": "L12",
    "name": "Beef W. Broccoli",
    "price": "8.25",
    "category": "Lunch Combos"
  },
  {
    "id": 116,
    "id_number": "L13",
    "name": "Chicken W. Broccoli",
    "price": "8.25",
    "category": "Lunch Combos"
  },
  {
    "id": 117,
    "id_number": "L14",
    "name": "Sesame Chicken",
    "price": "8.25",
    "category": "Lunch Combos"
  },
  {
    "id": 118,
    "id_number": "L15",
    "name": "Kung Po Chicken (Spicy)",
    "price": "8.25",
    "category": "Lunch Combos"
  },
  {
    "id": 119,
    "id_number": "L16",
    "name": "Shrimp W. Garlic Sauce (Spicy)",
    "price": "8.25",
    "category": "Lunch Combos"
  },
  {
    "id": 120,
    "id_number": "L17",
    "name": "Chicken W. Garlic Sauce (Spicy)",
    "price": "8.25",
    "category": "Lunch Combos"
  },
  {
    "id": 121,
    "id_number": "L18",
    "name": "Szechuan Spice Shrimp (Spicy)",
    "price": "8.25",
    "category": "Lunch Combos"
  },
  {
    "id": 122,
    "id_number": "L19",
    "name": "Sesame Beef",
    "price": "8.25",
    "category": "Lunch Combos"
  },
  {
    "id": 123,
    "id_number": "L20",
    "name": "General Tso's Chicken (Spicy)",
    "price": "8.25",
    "category": "Lunch Combos"
  },
  {
    "id": 124,
    "id_number": "L21",
    "name": "Chicken W. Cashew Nuts",
    "price": "8.25",
    "category": "Lunch Combos"
  },
  {
    "id": 125,
    "id_number": "L22",
    "name": "Beef Hunan Style (Spicy)",
    "price": "8.25",
    "category": "Lunch Combos"
  },
  {
    "id": 126,
    "id_number": "L23",
    "name": "Beef Szechuan Style (Spicy)",
    "price": "8.25",
    "category": "Lunch Combos"
  },
  {
    "id": 127,
    "id_number": "L24",
    "name": "Chicken Hunan Style (Spicy)",
    "price": "8.25",
    "category": "Lunch Combos"
  },
  {
    "id": 128,
    "id_number": "L25",
    "name": "Chicken Szechuan Style (Spicy)",
    "price": "8.25",
    "category": "Lunch Combos"
  },
  {
    "id": 129,
    "id_number": "L26",
    "name": "Hot & Spicy Chicken",
    "price": "8.25",
    "category": "Lunch Combos"
  },
  {
    "id": 130,
    "id_number": "L27",
    "name": "Hot & Spicy Shrimp",
    "price": "8.25",
    "category": "Lunch Combos"
  },
  {
    "id": 131,
    "id_number": "L28",
    "name": "Honey Chicken",
    "price": "8.25",
    "category": "Lunch Combos"
  },
  {
    "id": 132,
    "id_number": "L29",
    "name": "Chicken Teriyaki",
    "price": "8.25",
    "category": "Lunch Combos"
  },
  {
    "id": 133,
    "id_number": "L30",
    "name": "Black Pepper Chicken",
    "price": "8.25",
    "category": "Lunch Combos"
  },
  {
    "id": 134,
    "id_number": "L31",
    "name": "Bourbon Chicken",
    "price": "8.25",
    "category": "Lunch Combos"
  },
  {
    "id": 135,
    "id_number": "C1",
    "name": "Chicken Chow Mein",
    "price": "10.25",
    "category": "Special Combos"
  },
  {
    "id": 136,
    "id_number": "C2",
    "name": "Shrimp Chow Mein",
    "price": "10.25",
    "category": "Special Combos"
  },
  {
    "id": 137,
    "id_number": "C3",
    "name": "Roast Pork Egg Foo Young",
    "price": "10.25",
    "category": "Special Combos"
  },
  {
    "id": 138,
    "id_number": "C4",
    "name": "Roast Pork W. Chinese Veg",
    "price": "10.25",
    "category": "Special Combos"
  },
  {
    "id": 139,
    "id_number": "C5",
    "name": "Chicken Lo Mein (Soft Noodles)",
    "price": "10.25",
    "category": "Special Combos"
  },
  {
    "id": 140,
    "id_number": "C6",
    "name": "Pork Lo Mein (Soft Noodles)",
    "price": "10.25",
    "category": "Special Combos"
  },
  {
    "id": 141,
    "id_number": "C7",
    "name": "Pepper Steak W. Onion",
    "price": "10.25",
    "category": "Special Combos"
  },
  {
    "id": 142,
    "id_number": "C8",
    "name": "Moo Goo Gai Pan",
    "price": "10.25",
    "category": "Special Combos"
  },
  {
    "id": 143,
    "id_number": "C9",
    "name": "Sweet & Sour Chicken",
    "price": "10.25",
    "category": "Special Combos"
  },
  {
    "id": 144,
    "id_number": "C10",
    "name": "Shrimp W. Lobster Sauce",
    "price": "10.25",
    "category": "Special Combos"
  },
  {
    "id": 145,
    "id_number": "C11",
    "name": "Shrimp W. Broccoli",
    "price": "10.25",
    "category": "Special Combos"
  },
  {
    "id": 146,
    "id_number": "C12",
    "name": "Beef W. Broccoli",
    "price": "10.25",
    "category": "Special Combos"
  },
  {
    "id": 147,
    "id_number": "C13",
    "name": "Chicken W. Broccoli",
    "price": "10.25",
    "category": "Special Combos"
  },
  {
    "id": 148,
    "id_number": "C14",
    "name": "Sesame Chicken",
    "price": "10.25",
    "category": "Special Combos"
  },
  {
    "id": 149,
    "id_number": "C15",
    "name": "Kung Po Chicken (Spicy)",
    "price": "10.25",
    "category": "Special Combos"
  },
  {
    "id": 150,
    "id_number": "C16",
    "name": "Shrimp W. Garlic Sauce (Spicy)",
    "price": "10.25",
    "category": "Special Combos"
  },
  {
    "id": 151,
    "id_number": "C17",
    "name": "Chicken W. Garlic Sauce (Spicy)",
    "price": "10.25",
    "category": "Special Combos"
  },
  {
    "id": 152,
    "id_number": "C18",
    "name": "Szechuan Spice Shrimp (Spicy)",
    "price": "10.25",
    "category": "Special Combos"
  },
  {
    "id": 153,
    "id_number": "C19",
    "name": "Sesame Beef",
    "price": "10.25",
    "category": "Special Combos"
  },
  {
    "id": 154,
    "id_number": "C20",
    "name": "General Tso's Chicken (Spicy)",
    "price": "10.25",
    "category": "Special Combos"
  },
  {
    "id": 155,
    "id_number": "C21",
    "name": "Chicken W. Cashew Nuts",
    "price": "10.25",
    "category": "Special Combos"
  },
  {
    "id": 156,
    "id_number": "C22",
    "name": "Beef Hunan Style (Spicy)",
    "price": "10.25",
    "category": "Special Combos"
  },
  {
    "id": 157,
    "id_number": "C23",
    "name": "Beef Szechuan Style (Spicy)",
    "price": "10.25",
    "category": "Special Combos"
  },
  {
    "id": 158,
    "id_number": "C24",
    "name": "Chicken Hunan Style (Spicy)",
    "price": "10.25",
    "category": "Special Combos"
  },
  {
    "id": 159,
    "id_number": "C25",
    "name": "Chicken Szechuan Style (Spicy)",
    "price": "10.25",
    "category": "Special Combos"
  },
  {
    "id": 160,
    "id_number": "C26",
    "name": "Hot & Spicy Chicken",
    "price": "10.25",
    "category": "Special Combos"
  },
  {
    "id": 161,
    "id_number": "C27",
    "name": "Hot & Spicy Shrimp",
    "price": "10.25",
    "category": "Special Combos"
  },
  {
    "id": 162,
    "id_number": "C28",
    "name": "Honey Chicken",
    "price": "10.25",
    "category": "Special Combos"
  },
  {
    "id": 163,
    "id_number": "C29",
    "name": "Chicken Teriyaki",
    "price": "10.25",
    "category": "Special Combos"
  },
  {
    "id": 164,
    "id_number": "C30",
    "name": "Black Pepper Chicken",
    "price": "10.25",
    "category": "Special Combos"
  },
  {
    "id": 165,
    "id_number": "C31",
    "name": "Bourbon Chicken",
    "price": "10.25",
    "category": "Special Combos"
  },
  {
    "id": 166,
    "id_number": "S1",
    "name": "Happy Family",
    "price": "13.95",
    "category": "Chef Specials"
  },
  {
    "id": 167,
    "id_number": "S2",
    "name": "Seafood Combination",
    "price": "14.75",
    "category": "Chef Specials"
  },
  {
    "id": 168,
    "id_number": "S3",
    "name": "Mandarin Triple Crown",
    "price": "12.25",
    "category": "Chef Specials"
  },
  {
    "id": 169,
    "id_number": "S4",
    "name": "Double Treat",
    "price": "12.25",
    "category": "Chef Specials"
  },
  {
    "id": 170,
    "id_number": "S5",
    "name": "General Tso's Shrimp (Spicy)",
    "price": "11.95",
    "category": "Chef Specials"
  },
  {
    "id": 171,
    "id_number": "S6",
    "name": "Sesame Beef",
    "price": "12.50",
    "category": "Chef Specials"
  },
  {
    "id": 172,
    "id_number": "S7",
    "name": "Sesame Chicken",
    "price": "10.99",
    "category": "Chef Specials"
  },
  {
    "id": 173,
    "id_number": "S8",
    "name": "Hunan Shrimp (Spicy)",
    "price": "11.50",
    "category": "Chef Specials"
  },
  {
    "id": 174,
    "id_number": "S9",
    "name": "Dragon & Phoenix",
    "price": "11.75",
    "category": "Chef Specials"
  },
  {
    "id": 175,
    "id_number": "S10",
    "name": "General Tso's Chicken (Spicy)",
    "price": "11.50",
    "category": "Chef Specials"
  },
  {
    "id": 176,
    "id_number": "S11",
    "name": "Orange Chicken (Spicy)",
    "price": "11.59",
    "category": "Chef Specials"
  },
  {
    "id": 177,
    "id_number": "S12",
    "name": "Orange Beef (Spicy)",
    "price": "11.99",
    "category": "Chef Specials"
  },
  {
    "id": 178,
    "id_number": "S13",
    "name": "Triple Delight W. Garlic Sauce (Spicy)",
    "price": "10.75",
    "category": "Chef Specials"
  },
  {
    "id": 179,
    "id_number": "S14",
    "name": "Kung Po Triple Delight (Spicy)",
    "price": "11.75",
    "category": "Chef Specials"
  },
  {
    "id": 180,
    "id_number": "S15",
    "name": "Hunan Triple (Spicy)",
    "price": "11.75",
    "category": "Chef Specials"
  },
  {
    "id": 181,
    "id_number": "S16",
    "name": "Shrimp W. Szechuan Sauce (Spicy)",
    "price": "11.75",
    "category": "Chef Specials"
  },
  {
    "id": 182,
    "id_number": "S17",
    "name": "Mongolian Beef",
    "price": "11.75",
    "category": "Chef Specials"
  },
  {
    "id": 183,
    "id_number": "S18",
    "name": "Honey Chicken",
    "price": "11.75",
    "category": "Chef Specials"
  },
  {
    "id": 184,
    "id_number": "D1",
    "name": "Bean Curd & Mixed Vegetables",
    "price": "8.50",
    "category": "Diet Menu"
  },
  {
    "id": 185,
    "id_number": "D2",
    "name": "Mixed Vegetables",
    "price": "8.50",
    "category": "Diet Menu"
  },
  {
    "id": 186,
    "id_number": "D3",
    "name": "Steamed Shrimp W. Broccoli",
    "price": "10.50",
    "category": "Diet Menu"
  },
  {
    "id": 187,
    "id_number": "D4",
    "name": "Chicken W. Broccoli",
    "price": "9.95",
    "category": "Diet Menu"
  },
  {
    "id": 188,
    "id_number": "D5",
    "name": "Chicken W. Vegetables",
    "price": "9.95",
    "category": "Diet Menu"
  },
  {
    "id": 189,
    "id_number": "D6",
    "name": "Steamed Broccoli",
    "price": "8.50",
    "category": "Diet Menu"
  },
  {
    "id": 190,
    "id_number": "D7",
    "name": "Shrimp W. Chinese Vegetables",
    "price": "10.50",
    "category": "Diet Menu"
  },
  {
    "id": 191,
    "id_number": null,
    "name": "California Roll (8)",
    "price": "7.99",
    "category": "Sushi Rolls"
  },
  {
    "id": 192,
    "id_number": null,
    "name": "Pennsylvania Roll (8)",
    "price": "7.99",
    "category": "Sushi Rolls"
  },
  {
    "id": 193,
    "id_number": null,
    "name": "Special Roll (8)",
    "price": "8.99",
    "category": "Sushi Rolls"
  },
  {
    "id": 194,
    "id_number": null,
    "name": "Spicy Crabmeat Roll (8)",
    "price": "7.99",
    "category": "Sushi Rolls"
  },
  {
    "id": 195,
    "id_number": null,
    "name": "Coconut Crabmeat Roll (8)",
    "price": "7.99",
    "category": "Sushi Rolls"
  },
  {
    "id": 196,
    "id_number": null,
    "name": "Delivery Fee",
    "price": "1.00",
    "category": "Side Orders"
  },
  {
    "id": 197,
    "id_number": null,
    "name": "White Rice",
    "price": "3.50",
    "category": "Side Orders"
  },
  {
    "id": 198,
    "id_number": null,
    "name": "Fortune Cookies (10)",
    "price": "5.00",
    "category": "Side Orders"
  },
  {
    "id": 199,
    "id_number": null,
    "name": "Fried Noodles (Big Bag)",
    "price": "3.00",
    "category": "Side Orders"
  },
  {
    "id": 200,
    "id_number": null,
    "name": "Sauce",
    "price": "1.50",
    "category": "Side Orders"
  }
]
